[{"id":"ipt","sku":"yeeee","externalId":"","type":"epoxy","ean":"","custom":{},"name":{"default":"visualiser"},"description":{"default":""},"url":"","image":{"large":"https://d2xsg7d4c6iu77.cloudfront.net/account/1efrt/product/1e7cj/main__image_original__f8de9e8e.png","medium":"https://d2xsg7d4c6iu77.cloudfront.net/account/1efrt/product/1e7cj/main__image_thumbnail_512__9e014153.png","small":"https://d2xsg7d4c6iu77.cloudfront.net/account/1efrt/product/1e7cj/main__image_thumbnail_256__e34f06e9.png"},"rgbaColor":null,"countX":1,"countY":1,"totalCount":1,"combined":[{"image":{"large":"https://d2xsg7d4c6iu77.cloudfront.net/account/1efrt/product/ipt/variant/2dw9m/combined__image_2k__70079c89.png"},"countX":1,"countY":1,"totalCount":1}],"tileOptions":[{"id":"2dw9m","width":"20.00","height":"20.00","thickness":"30.00","weightPerBox":"0","wearLayerThickness":"20.00","unit":"MM","displayUnit":"CM","weightUnit":"unit_gram","url":"65","prices":[],"isDefault":true,"fugueSize":"0.00","fugueColor":"","fugueUnit":null,"fugueEditable":false,"tiles":[],"model3D":null}],"patterns":["basket","brick","chevron","grid","herringbone","random"],"defaultPattern":"basket","hardwoodVariant":{"gloss":null,"cutAngle":null,"woodType":null,"boardType":null,"colorTone":null},"productStructure":{"brush":null,"groove":null,"colorTone":null,"finishing":null,"noOfSlats":null,"structure":null,"areaPerBox":null,"noOfLayers":null,"noOfPcInBox":null,"floorHeating":null,"areaPerBoxUnit":null},"roomTypes":["bedroom","livingroom","childrenroom","kitchen","bathroom","other","antechamber","balcony","basement","cafe","cafeteria","changingroom","corridor","diningroom","drive","entrance","entresol","factory","garage","gym","hall","healthcare","homeoffice","hotel","mancave","office","reception","room","salon","school","shop","shoppingmall","staircase","studio","swimmingpool","terrace","warehouse","large_room","exteriors","industrial","laundry","lobby","commercial"],"placementOptions":["floors"],"installation":{"methods":null,"warrantYears":null,"baseIntegrated":null,"installationInstructions":""},"technicalParameters":{"hardness":null,"antistatic":null,"hdfDensity":null,"usageClass":null,"hardnessUnit":null,"hygieneClass":null,"uvResistance":null,"abrasionClass":null,"smokeEmission":null,"allergyFriendly":null,"waterResistance":null,"heatPermeability":null,"impactResistance":null,"abrasionResistance":null,"antibacterialCoating":null},"carpetRugDetails":{"color":null,"shape":null,"primer":null,"softTouch":null,"fleeceType":null,"pileWeight":null,"electrified":null,"fleeceWeave":null,"totalWeight":null,"bondingLayer":null,"comfortOfUse":null,"materialType":null,"dirtResistant":null,"mothResistant":null,"publicUtility":null,"foundationType":null,"weavingDensity":null,"waterAbsorption":null,"canBeUsedOnStairs":null,"antislipProperties":null,"productionTechnique":null,"useUnderWheelChairs":null,"antistaticProperties":null,"polipropylenFirstLayer":null},"supplier":"","manufacturer":"","attachmentUrl":null,"certificates":[],"certificateLink":"","gallery":[],"manufacturerId":"1efrt","showDimensions":true,"isGlossy":false,"orderSampleUrl":null}]